rexpand_pyutils_file/__init__.py
rexpand_pyutils_file/downloader.py
rexpand_pyutils_file/file_system.py
rexpand_pyutils_file/finder.py
rexpand_pyutils_file/reader.py
rexpand_pyutils_file/utils.py
rexpand_pyutils_file/writer.py
rexpand_pyutils_file-0.0.7.dist-info/METADATA
rexpand_pyutils_file-0.0.7.dist-info/WHEEL
rexpand_pyutils_file-0.0.7.dist-info/licenses/LICENSE
rexpand_pyutils_file-0.0.7.dist-info/RECORD
