Metadata-Version: 2.4
Name: rexpand-pyutils-file
Version: 0.0.7
Summary: Python utilities for file system operations
Project-URL: Homepage, https://github.com/expand-app/rexpand-pyutils-file
Project-URL: Bug Tracker, https://github.com/expand-app/rexpand-pyutils-file/issues
Project-URL: Documentation, https://github.com/expand-app/rexpand-pyutils-file#readme
Author-email: Shuo Feng <shuo.feng@expand.app>
License: MIT
License-File: LICENSE
Keywords: csv,download,excel,file,filesystem,html,io,json
Classifier: Development Status :: 4 - Beta
Classifier: Intended Audience :: Developers
Classifier: License :: OSI Approved :: MIT License
Classifier: Operating System :: OS Independent
Classifier: Programming Language :: Python :: 3
Classifier: Programming Language :: Python :: 3.11
Classifier: Topic :: Software Development :: Libraries :: Python Modules
Classifier: Topic :: System :: Filesystems
Requires-Python: >=3.11
Requires-Dist: numpy>=1.24.0
Requires-Dist: openpyxl>=3.1.0
Requires-Dist: pandas>=2.0.0
Requires-Dist: requests>=2.31.0
Provides-Extra: dev
Requires-Dist: black>=23.0.0; extra == 'dev'
Requires-Dist: build>=1.0.0; extra == 'dev'
Requires-Dist: flake8>=6.0.0; extra == 'dev'
Requires-Dist: mypy>=1.0.0; extra == 'dev'
Requires-Dist: pytest>=7.0.0; extra == 'dev'
Requires-Dist: twine>=4.0.0; extra == 'dev'
